impress/__init__.py
impress/conf.py
impress/directives.py
impress/funcs.py
impress/ghp.py
impress/layout.html
impress/monkeys.py
impress/theme.conf
impress/static/custom.css
impress/static/custom.js
impress/static/impress.css
impress/static/impress.js
impress/static/impressjs/.gitattributes
impress/static/impressjs/.gitignore
impress/static/impressjs/.jshintrc
impress/static/impressjs/.npmignore
impress/static/impressjs/CHANGELOG.md
impress/static/impressjs/DOCUMENTATION.md
impress/static/impressjs/LICENSE
impress/static/impressjs/README.md
impress/static/impressjs/apple-touch-icon.png
impress/static/impressjs/bower.json
impress/static/impressjs/circle.yml
impress/static/impressjs/favicon.png
impress/static/impressjs/index.html
impress/static/impressjs/karma.conf-sauce.js
impress/static/impressjs/karma.conf.js
impress/static/impressjs/package.json
impress/static/impressjs/.github/CONTRIBUTING.md
impress/static/impressjs/.github/ISSUE_TEMPLATE.md
impress/static/impressjs/.github/PULL_REQUEST_TEMPLATE.md
impress/static/impressjs/css/impress-demo.css
impress/static/impressjs/js/impress.js
impress/static/impressjs/test/bootstrap.js
impress/static/impressjs/test/core_tests.js
impress-1.6.dist-info/DESCRIPTION.rst
impress-1.6.dist-info/METADATA
impress-1.6.dist-info/RECORD
impress-1.6.dist-info/WHEEL
impress-1.6.dist-info/entry_points.txt
impress-1.6.dist-info/metadata.json
impress-1.6.dist-info/top_level.txt
