Metadata-Version: 2.0
Name: impress
Version: 1.6
Summary: Generate slides from rest files using sphinx and impress.js
Home-page: http://gawel.github.com/impress/
Author: Gael Pasgrimaud
Author-email: gael@gawel.org
License: MIT
Keywords: sphinx impress.js
Platform: UNKNOWN
Requires-Dist: Sphinx
